langauge/.env
langauge/__init__.py
langauge/cli.py
langauge/docker-compose.yml
langauge/core/__init__.py
langauge/core/database/Dockerfile
langauge/core/database/__init__.py
langauge/core/database/init-db.d/__init__.py
langauge/core/database/init-db.d/seed1.js
langauge/core/dispatcher/Dockerfile
langauge/core/dispatcher/__init__.py
langauge/core/dispatcher/requirements.txt
langauge/core/dispatcher/model/__init__.py
langauge/core/dispatcher/model/utils/__init__.py
langauge/core/dispatcher/model/utils/download_azure.py
langauge/core/dispatcher/options/__init__.py
langauge/core/dispatcher/options/pipeline_options.py
langauge/core/dispatcher/task/__init__.py
langauge/core/dispatcher/task/tasks.py
langauge/core/dispatcher/test/__init__.py
langauge/core/dispatcher/test/lanGauge_beam_base.py
langauge/core/queue/Dockerfile
langauge/core/queue/__init__.py
langauge/core/service/Dockerfile
langauge/core/service/__init__.py
langauge/core/service/configs.py
langauge/core/service/requirements.txt
langauge/core/service/run.py
langauge/core/service/endpoints/__init__.py
langauge/core/service/endpoints/config.py
langauge/core/service/endpoints/job_status.py
langauge/core/service/endpoints/ner.py
langauge/core/service/main/__init__.py
langauge/core/service/main/create_app.py
langauge/core/service/main/database.py
langauge/core/service/main/worker.py
langauge/docs/build/html/_sources/howtotest.rst.txt
langauge/docs/build/html/_sources/index.rst.txt
langauge/docs/build/html/_sources/installing.rst.txt
langauge/docs/build/html/_sources/overview.rst.txt
langauge/docs/build/html/_sources/_autosummary/core.database.rst.txt
langauge/docs/build/html/_sources/_autosummary/core.dispatcher.model.rst.txt
langauge/docs/build/html/_sources/_autosummary/core.dispatcher.model.utils.download_azure.rst.txt
langauge/docs/build/html/_sources/_autosummary/core.dispatcher.model.utils.rst.txt
langauge/docs/build/html/_sources/_autosummary/core.dispatcher.options.pipeline_options.rst.txt
langauge-0.0.3.dist-info/LICENSE
langauge-0.0.3.dist-info/METADATA
langauge-0.0.3.dist-info/WHEEL
langauge-0.0.3.dist-info/entry_points.txt
langauge-0.0.3.dist-info/top_level.txt
langauge-0.0.3.dist-info/RECORD
