Metadata-Version: 2.1
Name: langauge
Version: 0.0.3
Summary: LanGauge: 'gauge' the usefulness of open-source medical datasets
Home-page: https://github.com/flapmx/LanGauge-INTERNAL
Author: Flapmax
License: MIT
Keywords: AI,NLP,Flapmax
Platform: UNKNOWN
Classifier: License :: OSI Approved :: MIT License
Classifier: Programming Language :: Python :: 3.6
Requires-Python: >=3.6
Requires-Dist: click
Requires-Dist: rapydo-controller
